{"sketch":{"totalLength":"Skupna dolžina","distance":"Razdalja","elevation":"Višina","area":"Površina","rotation":"Vrtenje","orientation":"Usmerjenost","radius":"Polmer","scale":"Merilo","size":"Velikost","helpMessages2d":{"point":"Kliknite na karto za dodajanje točke.","polylineZeroVertices":"Kliknite na karto za začetek risanja.","polylineOneVertex":"Dvokliknite na karto za dokončanje.","polygonZeroVertices":"Kliknite na karto za začetek risanja.","polygonOneVertex":"Kliknite na karto za nadaljevanje risanja.","polygonTwoVertices":"Dvokliknite na karto za dokončanje."},"helpMessages3d":{"point":"Kliknite v 3D-prizoru, da dodate točko.","polylineZeroVertices":"Kliknite v 3D-prizoru, da začnete z risanjem.","polylineOneVertex":"Dvokliknite v 3D-prizoru za dokončanje.","polygonZeroVertices":"Kliknite v 3D-prizoru, da začnete z risanjem.","polygonOneVertex":"Kliknite v 3D-prizoru, da nadaljujete z risanjem.","polygonTwoVertices":"Dvokliknite v 3D-prizoru za dokončanje."}}}