{"sketch":{"totalLength":"Comprimento Total","distance":"Distância","elevation":"Elevação","area":"Área","rotation":"Rotação","orientation":"Orientação","radius":"Raio","scale":"Escala","size":"Tamanho","helpMessages2d":{"point":"Clique no mapa para adicionar um ponto.","polylineZeroVertices":"Clique no mapa para iniciar o desenho.","polylineOneVertex":"Clique duas vezes no mapa para concluir.","polygonZeroVertices":"Clique no mapa para iniciar o desenho.","polygonOneVertex":"Clique no mapa para continuar o desenho.","polygonTwoVertices":"Clique duas vezes no mapa para concluir."},"helpMessages3d":{"point":"Clique na cena para adicionar um ponto.","polylineZeroVertices":"Clique na cena para começar a desenhar.","polylineOneVertex":"Clique duas vezes na cena para concluir.","polygonZeroVertices":"Clique na cena para começar a desenhar.","polygonOneVertex":"Clique na cena para continuar a desenhar.","polygonTwoVertices":"Clique duas vezes na cena para concluir."}}}