{"widgetLabel":"Alaptérkép réteglistája","baseHeading":"Alap","basemapTitle":"Alaptérkép címe","referenceHeading":"Referencia","noReferenceLayers":"Nincsenek referenciarétegek","noBaseLayers":"Nincsenek alaprétegek","showLayer":"Réteg megjelenítése","hideLayer":"Réteg elrejtése","layerInvisibleAtScale":"Láthatatlan a jelenlegi méretaránynál","layerError":"Hiba történt a réteg betöltésekor.","untitledLayer":"Cím nélküli réteg","layerIncompatible":"Nem kompatibilis az alaptérképpel","layerIncompatibleTooltip":"A réteg térbeli referenciája nem kompatibilis az alaptérkép térbeli referenciájával."}