{"widgetLabel":"Meteo","widgetLabelAccessible":"Widget meteo","weatherType":"Tipo di meteo","error":{"unsupported":"Il meteo è supportato solo in SceneView.","localScene":"Il clima è disponibile solo nelle scene globali.","notVisible":"Il clima è visibile solo a bassa quota.","noAtmosphere":"Il clima è supportato solo se l'atmosfera è abilitata."},"sunny":{"label":"Sereno","cloudCover":"Copertura nubi"},"cloudy":{"label":"Nuvoloso","cloudCover":"Copertura nubi"},"rainy":{"label":"Rainy","cloudCover":"Copertura nubi","precipitation":"Precipitazione"},"snowy":{"label":"Nevoso","cloudCover":"Copertura nubi","precipitation":"Precipitazione","snowCover":"Copertura nevosa","snowCoverTooltip":"Copre le superfici con la neve (eccetto la mappa di base)."},"foggy":{"label":"Nebbia","fogStrength":"Densità nebbia"}}